[
    [
        [
            {
                "x": -0.21929313242435455,
                "y": -0.5423217415809631,
                "z": -0.2393798828125,
                "score": 0.9998840093612671,
                "name": "nose"
            },
            {
                "x": -0.2015339434146881,
                "y": -0.5710813999176025,
                "z": -0.25244140625,
                "score": 0.999843955039978,
                "name": "left_eye_inner"
            },
            {
                "x": -0.19912144541740417,
                "y": -0.5705982446670532,
                "z": -0.2420654296875,
                "score": 0.9998377561569214,
                "name": "left_eye"
            },
            {
                "x": -0.2003401815891266,
                "y": -0.5713364481925964,
                "z": -0.2452392578125,
                "score": 0.999891996383667,
                "name": "left_eye_outer"
            },
            {
                "x": -0.21543914079666138,
                "y": -0.5716054439544678,
                "z": -0.24365234375,
                "score": 0.999841570854187,
                "name": "right_eye_inner"
            },
            {
                "x": -0.21474024653434753,
                "y": -0.5712554454803467,
                "z": -0.2548828125,
                "score": 0.9998390674591064,
                "name": "right_eye"
            },
            {
                "x": -0.20681768655776978,
                "y": -0.5604656934738159,
                "z": -0.236083984375,
                "score": 0.9998601675033569,
                "name": "right_eye_outer"
            },
            {
                "x": -0.09125916659832001,
                "y": -0.6041299700737,
                "z": -0.2164306640625,
                "score": 0.9999110698699951,
                "name": "left_ear"
            },
            {
                "x": -0.17304882407188416,
                "y": -0.5217450857162476,
                "z": -0.11474609375,
                "score": 0.9995362758636475,
                "name": "right_ear"
            },
            {
                "x": -0.15762510895729065,
                "y": -0.551503598690033,
                "z": -0.2130126953125,
                "score": 0.9999426603317261,
                "name": "mouth_left"
            },
            {
                "x": -0.17278090119361877,
                "y": -0.5063239336013794,
                "z": -0.211181640625,
                "score": 0.9998464584350586,
                "name": "mouth_right"
            },
            {
                "x": 0.07005287706851959,
                "y": -0.4970444440841675,
                "z": -0.11651611328125,
                "score": 0.9999916553497314,
                "name": "left_shoulder"
            },
            {
                "x": -0.17015039920806885,
                "y": -0.47093620896339417,
                "z": 0.11822509765625,
                "score": 0.9998133778572083,
                "name": "right_shoulder"
            },
            {
                "x": 0.1932588517665863,
                "y": -0.31066635251045227,
                "z": -0.18505859375,
                "score": 0.9886244535446167,
                "name": "left_elbow"
            },
            {
                "x": -0.19528034329414368,
                "y": -0.17609618604183197,
                "z": 0.12451171875,
                "score": 0.4303867518901825,
                "name": "right_elbow"
            },
            {
                "x": 0.053703878074884415,
                "y": -0.17249968647956848,
                "z": -0.2342529296875,
                "score": 0.9949396848678589,
                "name": "left_wrist"
            },
            {
                "x": -0.3968701958656311,
                "y": -0.15037427842617035,
                "z": -0.0419921875,
                "score": 0.9329437017440796,
                "name": "right_wrist"
            },
            {
                "x": 0.0029710885137319565,
                "y": -0.15055039525032043,
                "z": -0.2481689453125,
                "score": 0.992452085018158,
                "name": "left_pinky"
            },
            {
                "x": -0.4167230427265167,
                "y": -0.17084789276123047,
                "z": -0.09088134765625,
                "score": 0.9478657245635986,
                "name": "right_pinky"
            },
            {
                "x": -0.04220524802803993,
                "y": -0.16773532330989838,
                "z": -0.251708984375,
                "score": 0.992452085018158,
                "name": "left_index"
            },
            {
                "x": -0.4361470937728882,
                "y": -0.22436709702014923,
                "z": -0.11700439453125,
                "score": 0.9505947232246399,
                "name": "right_index"
            },
            {
                "x": 0.03481076657772064,
                "y": -0.1581023782491684,
                "z": -0.23486328125,
                "score": 0.9822876453399658,
                "name": "left_thumb"
            },
            {
                "x": -0.4124949276447296,
                "y": -0.16975408792495728,
                "z": -0.06439208984375,
                "score": 0.9318356513977051,
                "name": "right_thumb"
            },
            {
                "x": 0.08377675712108612,
                "y": 0.0009641237556934357,
                "z": -0.033416748046875,
                "score": 0.9999687671661377,
                "name": "left_hip"
            },
            {
                "x": -0.08157030493021011,
                "y": -0.005242748185992241,
                "z": 0.036407470703125,
                "score": 0.9999496936798096,
                "name": "right_hip"
            },
            {
                "x": 0.13618820905685425,
                "y": 0.4275135397911072,
                "z": -0.11114501953125,
                "score": 0.9878528118133545,
                "name": "left_knee"
            },
            {
                "x": -0.25649183988571167,
                "y": 0.27761703729629517,
                "z": -0.046234130859375,
                "score": 0.9837850332260132,
                "name": "right_knee"
            },
            {
                "x": 0.2491839975118637,
                "y": 0.7441442608833313,
                "z": 0.08636474609375,
                "score": 0.9893474578857422,
                "name": "left_ankle"
            },
            {
                "x": -0.13240112364292145,
                "y": 0.653915524482727,
                "z": 0.11920166015625,
                "score": 0.9720456600189209,
                "name": "right_ankle"
            },
            {
                "x": 0.23676550388336182,
                "y": 0.7812495231628418,
                "z": 0.10931396484375,
                "score": 0.8858291506767273,
                "name": "left_heel"
            },
            {
                "x": -0.12270036339759827,
                "y": 0.6852961182594299,
                "z": 0.0970458984375,
                "score": 0.9099069833755493,
                "name": "right_heel"
            },
            {
                "x": 0.19131912291049957,
                "y": 0.8204187154769897,
                "z": 0.0697021484375,
                "score": 0.9827572107315063,
                "name": "left_foot_index"
            },
            {
                "x": -0.20451506972312927,
                "y": 0.7452177405357361,
                "z": 0.08062744140625,
                "score": 0.967348575592041,
                "name": "right_foot_index"
            }
        ],
        [
            {
                "x": -0.22549833357334137,
                "y": -0.5348972082138062,
                "z": -0.2394762486219406,
                "score": 0.9998729228973389,
                "name": "nose"
            },
            {
                "x": -0.20834971964359283,
                "y": -0.563552737236023,
                "z": -0.2543162703514099,
                "score": 0.9998275637626648,
                "name": "left_eye_inner"
            },
            {
                "x": -0.2056686282157898,
                "y": -0.5634046196937561,
                "z": -0.2441817820072174,
                "score": 0.9998167157173157,
                "name": "left_eye"
            },
            {
                "x": -0.20724715292453766,
                "y": -0.5637241005897522,
                "z": -0.24719373881816864,
                "score": 0.9998778700828552,
                "name": "left_eye_outer"
            },
            {
                "x": -0.22026710212230682,
                "y": -0.5638765096664429,
                "z": -0.24389074742794037,
                "score": 0.9998282790184021,
                "name": "right_eye_inner"
            },
            {
                "x": -0.2198818027973175,
                "y": -0.5634412169456482,
                "z": -0.2549791932106018,
                "score": 0.9998253583908081,
                "name": "right_eye"
            },
            {
                "x": -0.2125556319952011,
                "y": -0.5522175431251526,
                "z": -0.23615165054798126,
                "score": 0.9998512864112854,
                "name": "right_eye_outer"
            },
            {
                "x": -0.0911082774400711,
                "y": -0.5965828895568848,
                "z": -0.2264307737350464,
                "score": 0.9998996257781982,
                "name": "left_ear"
            },
            {
                "x": -0.1729147732257843,
                "y": -0.5145184993743896,
                "z": -0.11437579989433289,
                "score": 0.9995088577270508,
                "name": "right_ear"
            },
            {
                "x": -0.15974090993404388,
                "y": -0.5424322485923767,
                "z": -0.21465422213077545,
                "score": 0.9999362230300903,
                "name": "mouth_left"
            },
            {
                "x": -0.17621178925037384,
                "y": -0.49704694747924805,
                "z": -0.21085752546787262,
                "score": 0.9998331069946289,
                "name": "mouth_right"
            },
            {
                "x": 0.07350125163793564,
                "y": -0.49423378705978394,
                "z": -0.12088216096162796,
                "score": 0.9999911189079285,
                "name": "left_shoulder"
            },
            {
                "x": -0.1517905592918396,
                "y": -0.46617668867111206,
                "z": 0.11838728934526443,
                "score": 0.9998166561126709,
                "name": "right_shoulder"
            },
            {
                "x": 0.2181376963853836,
                "y": -0.31049203872680664,
                "z": -0.18538270890712738,
                "score": 0.9874422550201416,
                "name": "left_elbow"
            },
            {
                "x": -0.1871652454137802,
                "y": -0.1759238988161087,
                "z": 0.15491046011447906,
                "score": 0.42827606201171875,
                "name": "right_elbow"
            },
            {
                "x": 0.06148853898048401,
                "y": -0.1557459682226181,
                "z": -0.2067042887210846,
                "score": 0.993076741695404,
                "name": "left_wrist"
            },
            {
                "x": -0.3974875211715698,
                "y": -0.1444685012102127,
                "z": 0.0314677357673645,
                "score": 0.9348978996276855,
                "name": "right_wrist"
            },
            {
                "x": 0.008285089395940304,
                "y": -0.13396728038787842,
                "z": -0.21216104924678802,
                "score": 0.9896790981292725,
                "name": "left_pinky"
            },
            {
                "x": -0.41766196489334106,
                "y": -0.16492019593715668,
                "z": -0.009877573698759079,
                "score": 0.9488782286643982,
                "name": "right_pinky"
            },
            {
                "x": -0.0382513664662838,
                "y": -0.14778482913970947,
                "z": -0.2135452777147293,
                "score": 0.9894812107086182,
                "name": "left_index"
            },
            {
                "x": -0.4359981119632721,
                "y": -0.21380352973937988,
                "z": -0.03621690720319748,
                "score": 0.9514430165290833,
                "name": "right_index"
            },
            {
                "x": 0.040391191840171814,
                "y": -0.138691246509552,
                "z": -0.2042265385389328,
                "score": 0.975979745388031,
                "name": "left_thumb"
            },
            {
                "x": -0.413103848695755,
                "y": -0.16210640966892242,
                "z": 0.009280129335820675,
                "score": 0.9330594539642334,
                "name": "right_thumb"
            },
            {
                "x": 0.08320503681898117,
                "y": 0.0022027355153113604,
                "z": -0.03351311758160591,
                "score": 0.9999698400497437,
                "name": "left_hip"
            },
            {
                "x": -0.08103471994400024,
                "y": -0.006586072035133839,
                "z": 0.03646188601851463,
                "score": 0.9999522566795349,
                "name": "right_hip"
            },
            {
                "x": 0.14385361969470978,
                "y": 0.41933000087738037,
                "z": -0.1060936376452446,
                "score": 0.9877298474311829,
                "name": "left_knee"
            },
            {
                "x": -0.2876717448234558,
                "y": 0.25959035754203796,
                "z": -0.04974963888525963,
                "score": 0.9842332601547241,
                "name": "right_knee"
            },
            {
                "x": 0.2475951462984085,
                "y": 0.7337285280227661,
                "z": 0.11320270597934723,
                "score": 0.9893918037414551,
                "name": "left_ankle"
            },
            {
                "x": -0.14535483717918396,
                "y": 0.6246457099914551,
                "z": 0.11444628238677979,
                "score": 0.972811758518219,
                "name": "right_ankle"
            },
            {
                "x": 0.23387034237384796,
                "y": 0.7695096135139465,
                "z": 0.13810813426971436,
                "score": 0.8866883516311646,
                "name": "left_heel"
            },
            {
                "x": -0.1339404135942459,
                "y": 0.6540957093238831,
                "z": 0.09357648342847824,
                "score": 0.9126027822494507,
                "name": "right_heel"
            },
            {
                "x": 0.1915908306837082,
                "y": 0.8188278675079346,
                "z": 0.10248380899429321,
                "score": 0.9824560284614563,
                "name": "left_foot_index"
            },
            {
                "x": -0.2114744931459427,
                "y": 0.724679172039032,
                "z": 0.07697287201881409,
                "score": 0.9678552150726318,
                "name": "right_foot_index"
            }
        ],
        [
            {
                "x": -0.2342478632926941,
                "y": -0.5518041849136353,
                "z": -0.28104639053344727,
                "score": 0.9998757243156433,
                "name": "nose"
            },
            {
                "x": -0.2144264578819275,
                "y": -0.5794435143470764,
                "z": -0.2944408357143402,
                "score": 0.9998264312744141,
                "name": "left_eye_inner"
            },
            {
                "x": -0.21193280816078186,
                "y": -0.5788562297821045,
                "z": -0.2841905355453491,
                "score": 0.9998154640197754,
                "name": "left_eye"
            },
            {
                "x": -0.21338379383087158,
                "y": -0.5791298747062683,
                "z": -0.2866419553756714,
                "score": 0.9998766183853149,
                "name": "left_eye_outer"
            },
            {
                "x": -0.2286967784166336,
                "y": -0.582088828086853,
                "z": -0.28566229343414307,
                "score": 0.9998263716697693,
                "name": "right_eye_inner"
            },
            {
                "x": -0.22827158868312836,
                "y": -0.5807273387908936,
                "z": -0.29738789796829224,
                "score": 0.9998239874839783,
                "name": "right_eye"
            },
            {
                "x": -0.22186733782291412,
                "y": -0.5702158808708191,
                "z": -0.2771567106246948,
                "score": 0.9998486042022705,
                "name": "right_eye_outer"
            },
            {
                "x": -0.09636477380990982,
                "y": -0.6013400554656982,
                "z": -0.2551891505718231,
                "score": 0.9998997449874878,
                "name": "left_ear"
            },
            {
                "x": -0.18832767009735107,
                "y": -0.5284281969070435,
                "z": -0.15361063182353973,
                "score": 0.9994867444038391,
                "name": "right_ear"
            },
            {
                "x": -0.1693960428237915,
                "y": -0.5539859533309937,
                "z": -0.25464802980422974,
                "score": 0.9999359250068665,
                "name": "mouth_left"
            },
            {
                "x": -0.1895720511674881,
                "y": -0.5127015709877014,
                "z": -0.25351110100746155,
                "score": 0.9998318552970886,
                "name": "mouth_right"
            },
            {
                "x": 0.06116493046283722,
                "y": -0.49393048882484436,
                "z": -0.1471550166606903,
                "score": 0.9999914765357971,
                "name": "left_shoulder"
            },
            {
                "x": -0.16965802013874054,
                "y": -0.4714508056640625,
                "z": 0.08229797333478928,
                "score": 0.9998212456703186,
                "name": "right_shoulder"
            },
            {
                "x": 0.2039833962917328,
                "y": -0.31218287348747253,
                "z": -0.22025081515312195,
                "score": 0.9878728985786438,
                "name": "left_elbow"
            },
            {
                "x": -0.1871628612279892,
                "y": -0.17663857340812683,
                "z": 0.0988302230834961,
                "score": 0.4287267029285431,
                "name": "right_elbow"
            },
            {
                "x": 0.04585333541035652,
                "y": -0.16303502023220062,
                "z": -0.2683999538421631,
                "score": 0.9932898283004761,
                "name": "left_wrist"
            },
            {
                "x": -0.38985931873321533,
                "y": -0.1439288854598999,
                "z": -0.06348886340856552,
                "score": 0.9376824498176575,
                "name": "right_wrist"
            },
            {
                "x": -0.00835030060261488,
                "y": -0.13996489346027374,
                "z": -0.2829917073249817,
                "score": 0.9899386167526245,
                "name": "left_pinky"
            },
            {
                "x": -0.4107361137866974,
                "y": -0.1628994643688202,
                "z": -0.11302971839904785,
                "score": 0.9510143995285034,
                "name": "right_pinky"
            },
            {
                "x": -0.05930071696639061,
                "y": -0.15599288046360016,
                "z": -0.2870737612247467,
                "score": 0.9897423386573792,
                "name": "left_index"
            },
            {
                "x": -0.42623135447502136,
                "y": -0.2111583799123764,
                "z": -0.14237764477729797,
                "score": 0.9535714387893677,
                "name": "right_index"
            },
            {
                "x": 0.022789794951677322,
                "y": -0.14630480110645294,
                "z": -0.2687729597091675,
                "score": 0.9763794541358948,
                "name": "left_thumb"
            },
            {
                "x": -0.40449491143226624,
                "y": -0.16104084253311157,
                "z": -0.08761780709028244,
                "score": 0.9357070326805115,
                "name": "right_thumb"
            },
            {
                "x": 0.08341431617736816,
                "y": 0.0037193747702986,
                "z": -0.02992405742406845,
                "score": 0.9999668598175049,
                "name": "left_hip"
            },
            {
                "x": -0.08142033964395523,
                "y": -0.00837173406034708,
                "z": 0.033328283578157425,
                "score": 0.9999478459358215,
                "name": "right_hip"
            },
            {
                "x": 0.17200227081775665,
                "y": 0.4150250554084778,
                "z": -0.08588507771492004,
                "score": 0.9846283793449402,
                "name": "left_knee"
            },
            {
                "x": -0.3027212917804718,
                "y": 0.2306060940027237,
                "z": -0.05045388266444206,
                "score": 0.9824762344360352,
                "name": "right_knee"
            },
            {
                "x": 0.2699163556098938,
                "y": 0.7403402328491211,
                "z": 0.12427949905395508,
                "score": 0.9847244024276733,
                "name": "left_ankle"
            },
            {
                "x": -0.3419368267059326,
                "y": 0.6260855197906494,
                "z": 0.08582562953233719,
                "score": 0.9720556139945984,
                "name": "right_ankle"
            },
            {
                "x": 0.25616830587387085,
                "y": 0.7783409357070923,
                "z": 0.14684398472309113,
                "score": 0.8668349385261536,
                "name": "left_heel"
            },
            {
                "x": -0.3520330488681793,
                "y": 0.6580564975738525,
                "z": 0.06036175787448883,
                "score": 0.9118075370788574,
                "name": "right_heel"
            },
            {
                "x": 0.2262195646762848,
                "y": 0.8250530362129211,
                "z": 0.10375797748565674,
                "score": 0.9762465357780457,
                "name": "left_foot_index"
            },
            {
                "x": -0.4537512958049774,
                "y": 0.6905276775360107,
                "z": 0.02466847375035286,
                "score": 0.9670156240463257,
                "name": "right_foot_index"
            }
        ],
        [
            {
                "x": -0.2135991007089615,
                "y": -0.5405863523483276,
                "z": -0.31660187244415283,
                "score": 0.9998807907104492,
                "name": "nose"
            },
            {
                "x": -0.20048531889915466,
                "y": -0.5686061978340149,
                "z": -0.32855910062789917,
                "score": 0.9998245239257812,
                "name": "left_eye_inner"
            },
            {
                "x": -0.19802787899971008,
                "y": -0.5675066113471985,
                "z": -0.3185357451438904,
                "score": 0.9998126029968262,
                "name": "left_eye"
            },
            {
                "x": -0.1989331990480423,
                "y": -0.5678367614746094,
                "z": -0.3202577531337738,
                "score": 0.9998734593391418,
                "name": "left_eye_outer"
            },
            {
                "x": -0.21697072684764862,
                "y": -0.5693495869636536,
                "z": -0.3238193988800049,
                "score": 0.9998250603675842,
                "name": "right_eye_inner"
            },
            {
                "x": -0.21666161715984344,
                "y": -0.5673326849937439,
                "z": -0.33532899618148804,
                "score": 0.9998236298561096,
                "name": "right_eye"
            },
            {
                "x": -0.2102089822292328,
                "y": -0.5556307435035706,
                "z": -0.3154948353767395,
                "score": 0.9998480081558228,
                "name": "right_eye_outer"
            },
            {
                "x": -0.09442188590765,
                "y": -0.6008038520812988,
                "z": -0.2746288478374481,
                "score": 0.9998984336853027,
                "name": "left_ear"
            },
            {
                "x": -0.1958049237728119,
                "y": -0.5182990431785583,
                "z": -0.1906355619430542,
                "score": 0.999468982219696,
                "name": "right_ear"
            },
            {
                "x": -0.1511813849210739,
                "y": -0.5472114086151123,
                "z": -0.28433528542518616,
                "score": 0.9999340772628784,
                "name": "mouth_left"
            },
            {
                "x": -0.1750076860189438,
                "y": -0.5028280019760132,
                "z": -0.28767073154449463,
                "score": 0.9998292326927185,
                "name": "mouth_right"
            },
            {
                "x": 0.06118026375770569,
                "y": -0.4941001236438751,
                "z": -0.16618400812149048,
                "score": 0.9999920129776001,
                "name": "left_shoulder"
            },
            {
                "x": -0.17367923259735107,
                "y": -0.4763290584087372,
                "z": 0.06979687511920929,
                "score": 0.9998340010643005,
                "name": "right_shoulder"
            },
            {
                "x": 0.20033715665340424,
                "y": -0.30421289801597595,
                "z": -0.23074163496494293,
                "score": 0.9871436953544617,
                "name": "left_elbow"
            },
            {
                "x": -0.19672459363937378,
                "y": -0.18697591125965118,
                "z": 0.10477129369974136,
                "score": 0.4203535318374634,
                "name": "right_elbow"
            },
            {
                "x": 0.0333121195435524,
                "y": -0.15900787711143494,
                "z": -0.2608645260334015,
                "score": 0.9915139079093933,
                "name": "left_wrist"
            },
            {
                "x": -0.3965553343296051,
                "y": -0.14042514562606812,
                "z": -0.023510010913014412,
                "score": 0.9388530850410461,
                "name": "right_wrist"
            },
            {
                "x": -0.027644995599985123,
                "y": -0.13928569853305817,
                "z": -0.2749391198158264,
                "score": 0.9866645336151123,
                "name": "left_pinky"
            },
            {
                "x": -0.41872110962867737,
                "y": -0.15581314265727997,
                "z": -0.06451636552810669,
                "score": 0.9513181447982788,
                "name": "right_pinky"
            },
            {
                "x": -0.07710270583629608,
                "y": -0.1561071127653122,
                "z": -0.2839790880680084,
                "score": 0.9863000512123108,
                "name": "left_index"
            },
            {
                "x": -0.43212753534317017,
                "y": -0.2005990445613861,
                "z": -0.0921696349978447,
                "score": 0.9539897441864014,
                "name": "right_index"
            },
            {
                "x": 0.00985280703753233,
                "y": -0.14306718111038208,
                "z": -0.2612202763557434,
                "score": 0.9689680933952332,
                "name": "left_thumb"
            },
            {
                "x": -0.4119395613670349,
                "y": -0.15531107783317566,
                "z": -0.0450063981115818,
                "score": 0.9356945753097534,
                "name": "right_thumb"
            },
            {
                "x": 0.08261660486459732,
                "y": 0.005209778901189566,
                "z": -0.031488291919231415,
                "score": 0.9999644160270691,
                "name": "left_hip"
            },
            {
                "x": -0.08092380315065384,
                "y": -0.010182433761656284,
                "z": 0.03464563935995102,
                "score": 0.9999464750289917,
                "name": "right_hip"
            },
            {
                "x": 0.2038886696100235,
                "y": 0.41066721081733704,
                "z": -0.08218235522508621,
                "score": 0.9813339114189148,
                "name": "left_knee"
            },
            {
                "x": -0.30130383372306824,
                "y": 0.2336433231830597,
                "z": 0.00413136463612318,
                "score": 0.9770694971084595,
                "name": "right_knee"
            },
            {
                "x": 0.3595868647098541,
                "y": 0.7361696362495422,
                "z": 0.12928670644760132,
                "score": 0.9742802977561951,
                "name": "left_ankle"
            },
            {
                "x": -0.5015054941177368,
                "y": 0.6368758678436279,
                "z": 0.08767079561948776,
                "score": 0.9710891842842102,
                "name": "right_ankle"
            },
            {
                "x": 0.3553280532360077,
                "y": 0.77409827709198,
                "z": 0.1511458307504654,
                "score": 0.8380200862884521,
                "name": "left_heel"
            },
            {
                "x": -0.5300219058990479,
                "y": 0.6692378520965576,
                "z": 0.05874567851424217,
                "score": 0.9089100360870361,
                "name": "right_heel"
            },
            {
                "x": 0.3350367546081543,
                "y": 0.8189419507980347,
                "z": 0.10737279802560806,
                "score": 0.964891791343689,
                "name": "left_foot_index"
            },
            {
                "x": -0.6556788086891174,
                "y": 0.6511437892913818,
                "z": 0.004281158559024334,
                "score": 0.9665319323539734,
                "name": "right_foot_index"
            }
        ],
        [
            {
                "x": -0.256488174200058,
                "y": -0.5350727438926697,
                "z": -0.21632395684719086,
                "score": 0.9998789429664612,
                "name": "nose"
            },
            {
                "x": -0.24395769834518433,
                "y": -0.563495397567749,
                "z": -0.2363300621509552,
                "score": 0.9998066425323486,
                "name": "left_eye_inner"
            },
            {
                "x": -0.24171309173107147,
                "y": -0.5630737543106079,
                "z": -0.2273128777742386,
                "score": 0.9997909069061279,
                "name": "left_eye"
            },
            {
                "x": -0.24260565638542175,
                "y": -0.5634191036224365,
                "z": -0.2286141961812973,
                "score": 0.9998543858528137,
                "name": "left_eye_outer"
            },
            {
                "x": -0.2524349093437195,
                "y": -0.5645996332168579,
                "z": -0.22423239052295685,
                "score": 0.9998108148574829,
                "name": "right_eye_inner"
            },
            {
                "x": -0.25156405568122864,
                "y": -0.5626076459884644,
                "z": -0.23448102176189423,
                "score": 0.9998132586479187,
                "name": "right_eye"
            },
            {
                "x": -0.2449778914451599,
                "y": -0.5510998368263245,
                "z": -0.21543554961681366,
                "score": 0.9998412132263184,
                "name": "right_eye_outer"
            },
            {
                "x": -0.12731316685676575,
                "y": -0.597612738609314,
                "z": -0.22388288378715515,
                "score": 0.9998890161514282,
                "name": "left_ear"
            },
            {
                "x": -0.1998448669910431,
                "y": -0.515147864818573,
                "z": -0.1050555408000946,
                "score": 0.9994574785232544,
                "name": "right_ear"
            },
            {
                "x": -0.18856655061244965,
                "y": -0.5425373315811157,
                "z": -0.19874973595142365,
                "score": 0.9999280571937561,
                "name": "mouth_left"
            },
            {
                "x": -0.20223215222358704,
                "y": -0.496504545211792,
                "z": -0.19119752943515778,
                "score": 0.9998191595077515,
                "name": "mouth_right"
            },
            {
                "x": 0.04809379577636719,
                "y": -0.4893953204154968,
                "z": -0.12822313606739044,
                "score": 0.9999922513961792,
                "name": "left_shoulder"
            },
            {
                "x": -0.17108048498630524,
                "y": -0.47594714164733887,
                "z": 0.12505154311656952,
                "score": 0.9998461604118347,
                "name": "right_shoulder"
            },
            {
                "x": 0.18471501767635345,
                "y": -0.30256181955337524,
                "z": -0.17217053472995758,
                "score": 0.9849346876144409,
                "name": "left_elbow"
            },
            {
                "x": -0.2054353654384613,
                "y": -0.18859446048736572,
                "z": 0.17244002223014832,
                "score": 0.40526995062828064,
                "name": "right_elbow"
            },
            {
                "x": 0.027688300237059593,
                "y": -0.1540883332490921,
                "z": -0.1371898204088211,
                "score": 0.9828779697418213,
                "name": "left_wrist"
            },
            {
                "x": -0.41896021366119385,
                "y": -0.14074349403381348,
                "z": 0.0753105953335762,
                "score": 0.9366236925125122,
                "name": "right_wrist"
            },
            {
                "x": -0.02842296101152897,
                "y": -0.13441134989261627,
                "z": -0.13615061342716217,
                "score": 0.9731316566467285,
                "name": "left_pinky"
            },
            {
                "x": -0.44296762347221375,
                "y": -0.15570643544197083,
                "z": 0.04165622964501381,
                "score": 0.9485455751419067,
                "name": "right_pinky"
            },
            {
                "x": -0.07641222327947617,
                "y": -0.14746986329555511,
                "z": -0.13838335871696472,
                "score": 0.9717613458633423,
                "name": "left_index"
            },
            {
                "x": -0.45425811409950256,
                "y": -0.19979165494441986,
                "z": 0.01532812137156725,
                "score": 0.9513533711433411,
                "name": "right_index"
            },
            {
                "x": 0.006031493656337261,
                "y": -0.1374337077140808,
                "z": -0.13436958193778992,
                "score": 0.9439800381660461,
                "name": "left_thumb"
            },
            {
                "x": -0.43433454632759094,
                "y": -0.15531571209430695,
                "z": 0.055271316319704056,
                "score": 0.9323517084121704,
                "name": "right_thumb"
            },
            {
                "x": 0.08085857331752777,
                "y": 0.006230527069419622,
                "z": -0.03504180908203125,
                "score": 0.9999625086784363,
                "name": "left_hip"
            },
            {
                "x": -0.07940411567687988,
                "y": -0.011640073731541634,
                "z": 0.037849970161914825,
                "score": 0.9999464154243469,
                "name": "right_hip"
            },
            {
                "x": 0.2699635922908783,
                "y": 0.39703142642974854,
                "z": -0.10036756843328476,
                "score": 0.9786227941513062,
                "name": "left_knee"
            },
            {
                "x": -0.2981215715408325,
                "y": 0.2308495044708252,
                "z": 0.002738085575401783,
                "score": 0.971526563167572,
                "name": "right_knee"
            },
            {
                "x": 0.48942267894744873,
                "y": 0.6978213787078857,
                "z": 0.05322738364338875,
                "score": 0.9678429961204529,
                "name": "left_ankle"
            },
            {
                "x": -0.4590228497982025,
                "y": 0.6462448835372925,
                "z": 0.09352605044841766,
                "score": 0.9678266048431396,
                "name": "right_ankle"
            },
            {
                "x": 0.48967164754867554,
                "y": 0.7324491739273071,
                "z": 0.06832709163427353,
                "score": 0.813990592956543,
                "name": "left_heel"
            },
            {
                "x": -0.481986939907074,
                "y": 0.6815483570098877,
                "z": 0.06252571195363998,
                "score": 0.9036882519721985,
                "name": "right_heel"
            },
            {
                "x": 0.4552108347415924,
                "y": 0.76100093126297,
                "z": 0.009639068506658077,
                "score": 0.9561502933502197,
                "name": "left_foot_index"
            },
            {
                "x": -0.598278820514679,
                "y": 0.6597175598144531,
                "z": 0.008688072673976421,
                "score": 0.9637812376022339,
                "name": "right_foot_index"
            }
        ],
        [
            {
                "x": -0.2726016640663147,
                "y": -0.5087944865226746,
                "z": -0.16537337005138397,
                "score": 0.9998896718025208,
                "name": "nose"
            },
            {
                "x": -0.2641320526599884,
                "y": -0.5387208461761475,
                "z": -0.19343304634094238,
                "score": 0.9998230934143066,
                "name": "left_eye_inner"
            },
            {
                "x": -0.26237019896507263,
                "y": -0.5394455194473267,
                "z": -0.18430693447589874,
                "score": 0.9998090267181396,
                "name": "left_eye"
            },
            {
                "x": -0.26316800713539124,
                "y": -0.539810299873352,
                "z": -0.18562856316566467,
                "score": 0.9998664855957031,
                "name": "left_eye_outer"
            },
            {
                "x": -0.2671292722225189,
                "y": -0.541191816329956,
                "z": -0.17782895267009735,
                "score": 0.9998267889022827,
                "name": "right_eye_inner"
            },
            {
                "x": -0.26616522669792175,
                "y": -0.539785623550415,
                "z": -0.18782316148281097,
                "score": 0.9998293519020081,
                "name": "right_eye"
            },
            {
                "x": -0.2594921588897705,
                "y": -0.5279815793037415,
                "z": -0.16855782270431519,
                "score": 0.9998546838760376,
                "name": "right_eye_outer"
            },
            {
                "x": -0.15302568674087524,
                "y": -0.5856850743293762,
                "z": -0.20635101199150085,
                "score": 0.9998990893363953,
                "name": "left_ear"
            },
            {
                "x": -0.19938959181308746,
                "y": -0.5067054033279419,
                "z": -0.07406263053417206,
                "score": 0.9995067715644836,
                "name": "right_ear"
            },
            {
                "x": -0.20430664718151093,
                "y": -0.5223449468612671,
                "z": -0.15652717649936676,
                "score": 0.9999338388442993,
                "name": "mouth_left"
            },
            {
                "x": -0.2096635401248932,
                "y": -0.4760549068450928,
                "z": -0.1444321870803833,
                "score": 0.9998337030410767,
                "name": "mouth_right"
            },
            {
                "x": 0.02650189772248268,
                "y": -0.48486265540122986,
                "z": -0.13001173734664917,
                "score": 0.9999929070472717,
                "name": "left_shoulder"
            },
            {
                "x": -0.16025611758232117,
                "y": -0.4758669137954712,
                "z": 0.16333334147930145,
                "score": 0.9998586773872375,
                "name": "right_shoulder"
            },
            {
                "x": 0.15061381459236145,
                "y": -0.29599258303642273,
                "z": -0.17789801955223083,
                "score": 0.9861454367637634,
                "name": "left_elbow"
            },
            {
                "x": -0.19551575183868408,
                "y": -0.1887952983379364,
                "z": 0.21002812683582306,
                "score": 0.3966444730758667,
                "name": "right_elbow"
            },
            {
                "x": 0.0006138135795481503,
                "y": -0.14958985149860382,
                "z": -0.12196825444698334,
                "score": 0.9837257862091064,
                "name": "left_wrist"
            },
            {
                "x": -0.4093201458454132,
                "y": -0.14377650618553162,
                "z": 0.10831102728843689,
                "score": 0.9362800717353821,
                "name": "right_wrist"
            },
            {
                "x": -0.05172557383775711,
                "y": -0.12929503619670868,
                "z": -0.11684659868478775,
                "score": 0.9741463661193848,
                "name": "left_pinky"
            },
            {
                "x": -0.4338921904563904,
                "y": -0.1578182578086853,
                "z": 0.07839162647724152,
                "score": 0.9485160708427429,
                "name": "right_pinky"
            },
            {
                "x": -0.09568194299936295,
                "y": -0.1430494785308838,
                "z": -0.11746589839458466,
                "score": 0.9727411866188049,
                "name": "left_index"
            },
            {
                "x": -0.4447203576564789,
                "y": -0.20066840946674347,
                "z": 0.05120048299431801,
                "score": 0.9512866735458374,
                "name": "right_index"
            },
            {
                "x": -0.01759221963584423,
                "y": -0.1339624524116516,
                "z": -0.11734282970428467,
                "score": 0.9454898238182068,
                "name": "left_thumb"
            },
            {
                "x": -0.4249860942363739,
                "y": -0.15733900666236877,
                "z": 0.08757399767637253,
                "score": 0.9331188797950745,
                "name": "right_thumb"
            },
            {
                "x": 0.07496555894613266,
                "y": 0.0067726313136518,
                "z": -0.05084330961108208,
                "score": 0.9999629855155945,
                "name": "left_hip"
            },
            {
                "x": -0.07387081533670425,
                "y": -0.012373082339763641,
                "z": 0.05319035053253174,
                "score": 0.9999473094940186,
                "name": "right_hip"
            },
            {
                "x": 0.2885377109050751,
                "y": 0.3865616023540497,
                "z": -0.14235541224479675,
                "score": 0.9803795218467712,
                "name": "left_knee"
            },
            {
                "x": -0.30535393953323364,
                "y": 0.19563326239585876,
                "z": 0.005988163407891989,
                "score": 0.9718319177627563,
                "name": "right_knee"
            },
            {
                "x": 0.5767590999603271,
                "y": 0.6386624574661255,
                "z": -0.039066240191459656,
                "score": 0.9699810147285461,
                "name": "left_ankle"
            },
            {
                "x": -0.37177538871765137,
                "y": 0.6204139590263367,
                "z": 0.11031010001897812,
                "score": 0.9680224657058716,
                "name": "right_ankle"
            },
            {
                "x": 0.5834633111953735,
                "y": 0.6687553524971008,
                "z": -0.02883327566087246,
                "score": 0.8240664005279541,
                "name": "left_heel"
            },
            {
                "x": -0.3828478455543518,
                "y": 0.6569548845291138,
                "z": 0.07959844917058945,
                "score": 0.9086207747459412,
                "name": "right_heel"
            },
            {
                "x": 0.5185854434967041,
                "y": 0.7071563005447388,
                "z": -0.075367771089077,
                "score": 0.9590452909469604,
                "name": "left_foot_index"
            },
            {
                "x": -0.5041983127593994,
                "y": 0.6637363433837891,
                "z": 0.06284458190202713,
                "score": 0.9649561643600464,
                "name": "right_foot_index"
            }
        ],
        [
            {
                "x": -0.2845896780490875,
                "y": -0.527370274066925,
                "z": -0.2548312544822693,
                "score": 0.9998818635940552,
                "name": "nose"
            },
            {
                "x": -0.27068424224853516,
                "y": -0.5567194223403931,
                "z": -0.2747293710708618,
                "score": 0.9998036623001099,
                "name": "left_eye_inner"
            },
            {
                "x": -0.2686086595058441,
                "y": -0.5572664141654968,
                "z": -0.26471593976020813,
                "score": 0.9997907280921936,
                "name": "left_eye"
            },
            {
                "x": -0.2695346474647522,
                "y": -0.5570889115333557,
                "z": -0.26641327142715454,
                "score": 0.9998528957366943,
                "name": "left_eye_outer"
            },
            {
                "x": -0.2800183892250061,
                "y": -0.5588432550430298,
                "z": -0.26355230808258057,
                "score": 0.9998015761375427,
                "name": "right_eye_inner"
            },
            {
                "x": -0.2791232168674469,
                "y": -0.5575404167175293,
                "z": -0.2747773230075836,
                "score": 0.9998056292533875,
                "name": "right_eye"
            },
            {
                "x": -0.2726953625679016,
                "y": -0.5472541451454163,
                "z": -0.2547382116317749,
                "score": 0.999832808971405,
                "name": "right_eye_outer"
            },
            {
                "x": -0.15743058919906616,
                "y": -0.5899227857589722,
                "z": -0.2554008364677429,
                "score": 0.9998902082443237,
                "name": "left_ear"
            },
            {
                "x": -0.22596028447151184,
                "y": -0.5139495134353638,
                "z": -0.14319683611392975,
                "score": 0.999416172504425,
                "name": "right_ear"
            },
            {
                "x": -0.21925614774227142,
                "y": -0.5359795689582825,
                "z": -0.23551709949970245,
                "score": 0.9999241232872009,
                "name": "mouth_left"
            },
            {
                "x": -0.23105645179748535,
                "y": -0.49212607741355896,
                "z": -0.23050954937934875,
                "score": 0.9998082518577576,
                "name": "mouth_right"
            },
            {
                "x": 0.008853674866259098,
                "y": -0.48855289816856384,
                "z": -0.16562552750110626,
                "score": 0.9999929070472717,
                "name": "left_shoulder"
            },
            {
                "x": -0.20348884165287018,
                "y": -0.47510549426078796,
                "z": 0.0993678867816925,
                "score": 0.99985671043396,
                "name": "right_shoulder"
            },
            {
                "x": 0.1413797289133072,
                "y": -0.3102432191371918,
                "z": -0.22013263404369354,
                "score": 0.986248791217804,
                "name": "left_elbow"
            },
            {
                "x": -0.22235940396785736,
                "y": -0.18744459748268127,
                "z": 0.13339151442050934,
                "score": 0.3804733157157898,
                "name": "right_elbow"
            },
            {
                "x": -0.024720756337046623,
                "y": -0.15503352880477905,
                "z": -0.22064347565174103,
                "score": 0.9836089611053467,
                "name": "left_wrist"
            },
            {
                "x": -0.4180459678173065,
                "y": -0.14051291346549988,
                "z": 0.01275880727916956,
                "score": 0.9288291931152344,
                "name": "right_wrist"
            },
            {
                "x": -0.08190935850143433,
                "y": -0.13431233167648315,
                "z": -0.22917844355106354,
                "score": 0.9737045168876648,
                "name": "left_pinky"
            },
            {
                "x": -0.4393812417984009,
                "y": -0.1574867218732834,
                "z": -0.026267562061548233,
                "score": 0.9418259263038635,
                "name": "right_pinky"
            },
            {
                "x": -0.1330704391002655,
                "y": -0.15049581229686737,
                "z": -0.2288903445005417,
                "score": 0.9722570180892944,
                "name": "left_index"
            },
            {
                "x": -0.45651015639305115,
                "y": -0.20265167951583862,
                "z": -0.05253113433718681,
                "score": 0.9451109170913696,
                "name": "right_index"
            },
            {
                "x": -0.04722766578197479,
                "y": -0.13904185593128204,
                "z": -0.21814949810504913,
                "score": 0.9432030320167542,
                "name": "left_thumb"
            },
            {
                "x": -0.4341434836387634,
                "y": -0.15629436075687408,
                "z": -0.00827032420784235,
                "score": 0.9251372814178467,
                "name": "right_thumb"
            },
            {
                "x": 0.07890090346336365,
                "y": 0.0033879459369927645,
                "z": -0.04433463141322136,
                "score": 0.999959409236908,
                "name": "left_hip"
            },
            {
                "x": -0.07772252708673477,
                "y": -0.008564379997551441,
                "z": 0.047100286930799484,
                "score": 0.9999431371688843,
                "name": "right_hip"
            },
            {
                "x": 0.28294700384140015,
                "y": 0.37433770298957825,
                "z": -0.13462761044502258,
                "score": 0.9766658544540405,
                "name": "left_knee"
            },
            {
                "x": -0.2923884391784668,
                "y": 0.2182094007730484,
                "z": -0.024179788306355476,
                "score": 0.9679186344146729,
                "name": "right_knee"
            },
            {
                "x": 0.5576796531677246,
                "y": 0.6338213086128235,
                "z": 0.07125015556812286,
                "score": 0.9569299817085266,
                "name": "left_ankle"
            },
            {
                "x": -0.3194807171821594,
                "y": 0.6440373659133911,
                "z": 0.092702217400074,
                "score": 0.9639301896095276,
                "name": "right_ankle"
            },
            {
                "x": 0.5705660581588745,
                "y": 0.665621280670166,
                "z": 0.09265469759702682,
                "score": 0.7854450941085815,
                "name": "left_heel"
            },
            {
                "x": -0.328528493642807,
                "y": 0.6798555254936218,
                "z": 0.06542745232582092,
                "score": 0.903475821018219,
                "name": "right_heel"
            },
            {
                "x": 0.48977380990982056,
                "y": 0.7145744562149048,
                "z": 0.049007855355739594,
                "score": 0.9417374134063721,
                "name": "left_foot_index"
            },
            {
                "x": -0.4366682469844818,
                "y": 0.7005466222763062,
                "z": 0.034628309309482574,
                "score": 0.9606947898864746,
                "name": "right_foot_index"
            }
        ],
        [
            {
                "x": -0.28609031438827515,
                "y": -0.5230222344398499,
                "z": -0.24578343331813812,
                "score": 0.9998763799667358,
                "name": "nose"
            },
            {
                "x": -0.27085503935813904,
                "y": -0.5510338544845581,
                "z": -0.25886520743370056,
                "score": 0.9997861981391907,
                "name": "left_eye_inner"
            },
            {
                "x": -0.2688138782978058,
                "y": -0.5515937209129333,
                "z": -0.2476559430360794,
                "score": 0.9997720122337341,
                "name": "left_eye"
            },
            {
                "x": -0.2700231671333313,
                "y": -0.5512185096740723,
                "z": -0.25028207898139954,
                "score": 0.9998384714126587,
                "name": "left_eye_outer"
            },
            {
                "x": -0.2831715941429138,
                "y": -0.554775595664978,
                "z": -0.25218841433525085,
                "score": 0.9997884035110474,
                "name": "right_eye_inner"
            },
            {
                "x": -0.28258568048477173,
                "y": -0.5534273982048035,
                "z": -0.2629183530807495,
                "score": 0.9997963905334473,
                "name": "right_eye"
            },
            {
                "x": -0.2755923271179199,
                "y": -0.5436578989028931,
                "z": -0.24361974000930786,
                "score": 0.999824583530426,
                "name": "right_eye_outer"
            },
            {
                "x": -0.16212792694568634,
                "y": -0.5832674503326416,
                "z": -0.22031442821025848,
                "score": 0.9998813271522522,
                "name": "left_ear"
            },
            {
                "x": -0.24063146114349365,
                "y": -0.5102518200874329,
                "z": -0.1283101588487625,
                "score": 0.9993862509727478,
                "name": "right_ear"
            },
            {
                "x": -0.22494085133075714,
                "y": -0.5320591330528259,
                "z": -0.2182919681072235,
                "score": 0.9999173879623413,
                "name": "mouth_left"
            },
            {
                "x": -0.23859481513500214,
                "y": -0.48920199275016785,
                "z": -0.22071848809719086,
                "score": 0.9997944235801697,
                "name": "mouth_right"
            },
            {
                "x": -0.0028215281199663877,
                "y": -0.48339784145355225,
                "z": -0.12725074589252472,
                "score": 0.9999922513961792,
                "name": "left_shoulder"
            },
            {
                "x": -0.22258591651916504,
                "y": -0.4638068675994873,
                "z": 0.10658534616231918,
                "score": 0.9998554587364197,
                "name": "right_shoulder"
            },
            {
                "x": 0.12268166989088058,
                "y": -0.306315153837204,
                "z": -0.1694500595331192,
                "score": 0.9862654805183411,
                "name": "left_elbow"
            },
            {
                "x": -0.21301010251045227,
                "y": -0.17111849784851074,
                "z": 0.12074120342731476,
                "score": 0.3814851939678192,
                "name": "right_elbow"
            },
            {
                "x": -0.04486529156565666,
                "y": -0.1552581936120987,
                "z": -0.15953251719474792,
                "score": 0.9832685589790344,
                "name": "left_wrist"
            },
            {
                "x": -0.4125424027442932,
                "y": -0.12612925469875336,
                "z": -0.035726554691791534,
                "score": 0.9298933148384094,
                "name": "right_wrist"
            },
            {
                "x": -0.1047179102897644,
                "y": -0.13352982699871063,
                "z": -0.161660835146904,
                "score": 0.9728129506111145,
                "name": "left_pinky"
            },
            {
                "x": -0.4358283281326294,
                "y": -0.14446218311786652,
                "z": -0.08141862601041794,
                "score": 0.9426196217536926,
                "name": "right_pinky"
            },
            {
                "x": -0.14893434941768646,
                "y": -0.14986328780651093,
                "z": -0.16453249752521515,
                "score": 0.9712986350059509,
                "name": "left_index"
            },
            {
                "x": -0.4559832215309143,
                "y": -0.191188782453537,
                "z": -0.10480015724897385,
                "score": 0.9457502365112305,
                "name": "right_index"
            },
            {
                "x": -0.06394520401954651,
                "y": -0.13988442718982697,
                "z": -0.1574416607618332,
                "score": 0.9411727786064148,
                "name": "left_thumb"
            },
            {
                "x": -0.43059009313583374,
                "y": -0.14253661036491394,
                "z": -0.056312281638383865,
                "score": 0.9260510802268982,
                "name": "right_thumb"
            },
            {
                "x": 0.07858921587467194,
                "y": 0.002703310688957572,
                "z": -0.040365975350141525,
                "score": 0.9999577403068542,
                "name": "left_hip"
            },
            {
                "x": -0.0774591714143753,
                "y": -0.007622813805937767,
                "z": 0.04361386224627495,
                "score": 0.9999416470527649,
                "name": "right_hip"
            },
            {
                "x": 0.1687367707490921,
                "y": 0.39963477849960327,
                "z": -0.12328875064849854,
                "score": 0.9775035381317139,
                "name": "left_knee"
            },
            {
                "x": -0.2848019003868103,
                "y": 0.24746626615524292,
                "z": -0.024850919842720032,
                "score": 0.9684303998947144,
                "name": "right_knee"
            },
            {
                "x": 0.3320370316505432,
                "y": 0.7179567217826843,
                "z": 0.0660889744758606,
                "score": 0.9579346179962158,
                "name": "left_ankle"
            },
            {
                "x": -0.2796872556209564,
                "y": 0.679037868976593,
                "z": 0.09306490421295166,
                "score": 0.9652828574180603,
                "name": "right_ankle"
            },
            {
                "x": 0.3249143958091736,
                "y": 0.7570330500602722,
                "z": 0.08583604544401169,
                "score": 0.7823920845985413,
                "name": "left_heel"
            },
            {
                "x": -0.28725841641426086,
                "y": 0.7161592841148376,
                "z": 0.06564359366893768,
                "score": 0.9065076112747192,
                "name": "right_heel"
            },
            {
                "x": 0.28035473823547363,
                "y": 0.7930986881256104,
                "z": 0.039982546120882034,
                "score": 0.9419607520103455,
                "name": "left_foot_index"
            },
            {
                "x": -0.40955591201782227,
                "y": 0.7324205040931702,
                "z": 0.03377479687333107,
                "score": 0.9615049958229065,
                "name": "right_foot_index"
            }
        ],
        [
            {
                "x": -0.2713041603565216,
                "y": -0.5262519717216492,
                "z": -0.248722106218338,
                "score": 0.999859631061554,
                "name": "nose"
            },
            {
                "x": -0.2535441517829895,
                "y": -0.5538419485092163,
                "z": -0.26260820031166077,
                "score": 0.9997522830963135,
                "name": "left_eye_inner"
            },
            {
                "x": -0.25176557898521423,
                "y": -0.5543726086616516,
                "z": -0.2518419027328491,
                "score": 0.9997384548187256,
                "name": "left_eye"
            },
            {
                "x": -0.25328564643859863,
                "y": -0.5539268255233765,
                "z": -0.2542048394680023,
                "score": 0.999814510345459,
                "name": "left_eye_outer"
            },
            {
                "x": -0.27011266350746155,
                "y": -0.5566302537918091,
                "z": -0.25376418232917786,
                "score": 0.9997580051422119,
                "name": "right_eye_inner"
            },
            {
                "x": -0.26952144503593445,
                "y": -0.5556097030639648,
                "z": -0.26467135548591614,
                "score": 0.9997719526290894,
                "name": "right_eye"
            },
            {
                "x": -0.26160818338394165,
                "y": -0.5454582571983337,
                "z": -0.24547427892684937,
                "score": 0.9998025894165039,
                "name": "right_eye_outer"
            },
            {
                "x": -0.14198721945285797,
                "y": -0.589502215385437,
                "z": -0.2214319407939911,
                "score": 0.9998633861541748,
                "name": "left_ear"
            },
            {
                "x": -0.22722187638282776,
                "y": -0.5116612911224365,
                "z": -0.12736786901950836,
                "score": 0.999301552772522,
                "name": "right_ear"
            },
            {
                "x": -0.20975282788276672,
                "y": -0.5371787548065186,
                "z": -0.2206566482782364,
                "score": 0.9999094009399414,
                "name": "mouth_left"
            },
            {
                "x": -0.22466415166854858,
                "y": -0.4936579167842865,
                "z": -0.2210937738418579,
                "score": 0.9997737407684326,
                "name": "mouth_right"
            },
            {
                "x": 0.027333976700901985,
                "y": -0.49495869874954224,
                "z": -0.12564778327941895,
                "score": 0.9999917149543762,
                "name": "left_shoulder"
            },
            {
                "x": -0.22004543244838715,
                "y": -0.4646960198879242,
                "z": 0.10719005018472672,
                "score": 0.9998539686203003,
                "name": "right_shoulder"
            },
            {
                "x": 0.1492476761341095,
                "y": -0.31424060463905334,
                "z": -0.18180438876152039,
                "score": 0.9865144491195679,
                "name": "left_elbow"
            },
            {
                "x": -0.20120131969451904,
                "y": -0.16650088131427765,
                "z": 0.09045649319887161,
                "score": 0.38477322459220886,
                "name": "right_elbow"
            },
            {
                "x": -0.021302619948983192,
                "y": -0.16983255743980408,
                "z": -0.21798188984394073,
                "score": 0.9838172197341919,
                "name": "left_wrist"
            },
            {
                "x": -0.3951997458934784,
                "y": -0.1287744790315628,
                "z": -0.11517384648323059,
                "score": 0.9309938549995422,
                "name": "right_wrist"
            },
            {
                "x": -0.08214667439460754,
                "y": -0.1436745822429657,
                "z": -0.22952835261821747,
                "score": 0.9737536311149597,
                "name": "left_pinky"
            },
            {
                "x": -0.417126327753067,
                "y": -0.14785072207450867,
                "z": -0.1714799553155899,
                "score": 0.943988561630249,
                "name": "right_pinky"
            },
            {
                "x": -0.12565241754055023,
                "y": -0.1638282686471939,
                "z": -0.23478318750858307,
                "score": 0.9723701477050781,
                "name": "left_index"
            },
            {
                "x": -0.4372318983078003,
                "y": -0.20036451518535614,
                "z": -0.1940227895975113,
                "score": 0.9470367431640625,
                "name": "right_index"
            },
            {
                "x": -0.040366776287555695,
                "y": -0.15660613775253296,
                "z": -0.21718436479568481,
                "score": 0.9430990219116211,
                "name": "left_thumb"
            },
            {
                "x": -0.4119952917098999,
                "y": -0.14689607918262482,
                "z": -0.1368146687746048,
                "score": 0.9275140762329102,
                "name": "right_thumb"
            },
            {
                "x": 0.07968764752149582,
                "y": 0.0018324931152164936,
                "z": -0.03572339192032814,
                "score": 0.9999567866325378,
                "name": "left_hip"
            },
            {
                "x": -0.0785699412226677,
                "y": -0.006588607560843229,
                "z": 0.03926520049571991,
                "score": 0.9999409914016724,
                "name": "right_hip"
            },
            {
                "x": 0.08736727386713028,
                "y": 0.4086124300956726,
                "z": -0.12251311540603638,
                "score": 0.978308379650116,
                "name": "left_knee"
            },
            {
                "x": -0.25405794382095337,
                "y": 0.27561041712760925,
                "z": -0.03895382955670357,
                "score": 0.969836413860321,
                "name": "right_knee"
            },
            {
                "x": 0.17871364951133728,
                "y": 0.7311850786209106,
                "z": 0.07136470079421997,
                "score": 0.9601272940635681,
                "name": "left_ankle"
            },
            {
                "x": -0.22736582159996033,
                "y": 0.6954196691513062,
                "z": 0.09277649223804474,
                "score": 0.9672986268997192,
                "name": "right_ankle"
            },
            {
                "x": 0.16293108463287354,
                "y": 0.7699710130691528,
                "z": 0.09328150004148483,
                "score": 0.7850049734115601,
                "name": "left_heel"
            },
            {
                "x": -0.23163051903247833,
                "y": 0.7306979894638062,
                "z": 0.06582130491733551,
                "score": 0.9098702073097229,
                "name": "right_heel"
            },
            {
                "x": 0.09594457596540451,
                "y": 0.8138433694839478,
                "z": 0.04349540174007416,
                "score": 0.9449318647384644,
                "name": "left_foot_index"
            },
            {
                "x": -0.3333244025707245,
                "y": 0.758452832698822,
                "z": 0.031211616471409798,
                "score": 0.9634998440742493,
                "name": "right_foot_index"
            }
        ],
        [
            {
                "x": -0.23052531480789185,
                "y": -0.5427234768867493,
                "z": -0.26315245032310486,
                "score": 0.9998542666435242,
                "name": "nose"
            },
            {
                "x": -0.2161855846643448,
                "y": -0.5713934302330017,
                "z": -0.2783096730709076,
                "score": 0.9997419118881226,
                "name": "left_eye_inner"
            },
            {
                "x": -0.21350637078285217,
                "y": -0.5710868835449219,
                "z": -0.26751604676246643,
                "score": 0.9997318387031555,
                "name": "left_eye"
            },
            {
                "x": -0.21505756676197052,
                "y": -0.5711714029312134,
                "z": -0.26953640580177307,
                "score": 0.9998084902763367,
                "name": "left_eye_outer"
            },
            {
                "x": -0.23010382056236267,
                "y": -0.5724327564239502,
                "z": -0.2705601453781128,
                "score": 0.9997469186782837,
                "name": "right_eye_inner"
            },
            {
                "x": -0.22929829359054565,
                "y": -0.5716173648834229,
                "z": -0.28199514746665955,
                "score": 0.9997637271881104,
                "name": "right_eye"
            },
            {
                "x": -0.22133685648441315,
                "y": -0.5609943866729736,
                "z": -0.2625046670436859,
                "score": 0.999794065952301,
                "name": "right_eye_outer"
            },
            {
                "x": -0.11181328445672989,
                "y": -0.6068912148475647,
                "z": -0.23818978667259216,
                "score": 0.9998597502708435,
                "name": "left_ear"
            },
            {
                "x": -0.19124434888362885,
                "y": -0.5236202478408813,
                "z": -0.14516204595565796,
                "score": 0.9992848038673401,
                "name": "right_ear"
            },
            {
                "x": -0.1713554561138153,
                "y": -0.553435742855072,
                "z": -0.23452205955982208,
                "score": 0.999905526638031,
                "name": "mouth_left"
            },
            {
                "x": -0.18551331758499146,
                "y": -0.5082935094833374,
                "z": -0.2358883023262024,
                "score": 0.999760091304779,
                "name": "mouth_right"
            },
            {
                "x": 0.05103694647550583,
                "y": -0.5060404539108276,
                "z": -0.14811080694198608,
                "score": 0.9999917149543762,
                "name": "left_shoulder"
            },
            {
                "x": -0.1759876161813736,
                "y": -0.4868721663951874,
                "z": 0.0992361381649971,
                "score": 0.9998517036437988,
                "name": "right_shoulder"
            },
            {
                "x": 0.17044030129909515,
                "y": -0.32428187131881714,
                "z": -0.21032021939754486,
                "score": 0.9872437119483948,
                "name": "left_elbow"
            },
            {
                "x": -0.15339148044586182,
                "y": -0.19047147035598755,
                "z": 0.09530821442604065,
                "score": 0.37547463178634644,
                "name": "right_elbow"
            },
            {
                "x": 0.0004956466727890074,
                "y": -0.1721774935722351,
                "z": -0.2349420189857483,
                "score": 0.9847424030303955,
                "name": "left_wrist"
            },
            {
                "x": -0.3675893545150757,
                "y": -0.12967228889465332,
                "z": -0.05026187002658844,
                "score": 0.9251183271408081,
                "name": "right_wrist"
            },
            {
                "x": -0.059173282235860825,
                "y": -0.14559122920036316,
                "z": -0.24412575364112854,
                "score": 0.9752140641212463,
                "name": "left_pinky"
            },
            {
                "x": -0.3937537968158722,
                "y": -0.14392484724521637,
                "z": -0.09000317752361298,
                "score": 0.9403209090232849,
                "name": "right_pinky"
            },
            {
                "x": -0.10730892419815063,
                "y": -0.16677604615688324,
                "z": -0.24891862273216248,
                "score": 0.9739999771118164,
                "name": "left_index"
            },
            {
                "x": -0.4209664463996887,
                "y": -0.18974149227142334,
                "z": -0.117635577917099,
                "score": 0.9435297846794128,
                "name": "right_index"
            },
            {
                "x": -0.020439134910702705,
                "y": -0.15844294428825378,
                "z": -0.2341490238904953,
                "score": 0.94636070728302,
                "name": "left_thumb"
            },
            {
                "x": -0.3873403072357178,
                "y": -0.14674213528633118,
                "z": -0.07282162457704544,
                "score": 0.9235026836395264,
                "name": "right_thumb"
            },
            {
                "x": 0.07854382693767548,
                "y": 0.004217096604406834,
                "z": -0.03878781199455261,
                "score": 0.999957799911499,
                "name": "left_hip"
            },
            {
                "x": -0.07713282853364944,
                "y": -0.008851902559399605,
                "z": 0.04179472103714943,
                "score": 0.9999425411224365,
                "name": "right_hip"
            },
            {
                "x": 0.03586162254214287,
                "y": 0.42040225863456726,
                "z": -0.12818792462348938,
                "score": 0.9794204831123352,
                "name": "left_knee"
            },
            {
                "x": -0.2562783360481262,
                "y": 0.2895110547542572,
                "z": -0.0431441105902195,
                "score": 0.9717326760292053,
                "name": "right_knee"
            },
            {
                "x": 0.18781161308288574,
                "y": 0.7280193567276001,
                "z": 0.09120319783687592,
                "score": 0.961928129196167,
                "name": "left_ankle"
            },
            {
                "x": -0.17298826575279236,
                "y": 0.7062235474586487,
                "z": 0.04780945926904678,
                "score": 0.9693160057067871,
                "name": "right_ankle"
            },
            {
                "x": 0.17897675931453705,
                "y": 0.7650228142738342,
                "z": 0.11670451611280441,
                "score": 0.7892454862594604,
                "name": "left_heel"
            },
            {
                "x": -0.16938897967338562,
                "y": 0.7409828305244446,
                "z": 0.019202666357159615,
                "score": 0.9141845107078552,
                "name": "right_heel"
            },
            {
                "x": 0.10183229297399521,
                "y": 0.8209520578384399,
                "z": 0.08631716668605804,
                "score": 0.9474682807922363,
                "name": "left_foot_index"
            },
            {
                "x": -0.27544713020324707,
                "y": 0.7825851440429688,
                "z": -0.011675034649670124,
                "score": 0.9656541347503662,
                "name": "right_foot_index"
            }
        ]
    ]
]